pytfe/__init__.py
pytfe/_http.py
pytfe/_jsonapi.py
pytfe/client.py
pytfe/config.py
pytfe/errors.py
pytfe/py.typed
pytfe/utils.py
pytfe/models/__init__.py
pytfe/models/agent.py
pytfe/models/apply.py
pytfe/models/comment.py
pytfe/models/common.py
pytfe/models/configuration_version.py
pytfe/models/cost_estimate.py
pytfe/models/data_retention_policy.py
pytfe/models/notification_configuration.py
pytfe/models/oauth_client.py
pytfe/models/oauth_token.py
pytfe/models/organization.py
pytfe/models/organization_membership.py
pytfe/models/plan.py
pytfe/models/plan_export.py
pytfe/models/policy.py
pytfe/models/policy_check.py
pytfe/models/policy_evaluation.py
pytfe/models/policy_set.py
pytfe/models/policy_set_outcome.py
pytfe/models/policy_set_parameter.py
pytfe/models/policy_set_version.py
pytfe/models/policy_types.py
pytfe/models/project.py
pytfe/models/query_run.py
pytfe/models/registry_module.py
pytfe/models/registry_provider.py
pytfe/models/reserved_tag_key.py
pytfe/models/run.py
pytfe/models/run_event.py
pytfe/models/run_task.py
pytfe/models/run_trigger.py
pytfe/models/ssh_key.py
pytfe/models/state_version.py
pytfe/models/state_version_output.py
pytfe/models/task_stage.py
pytfe/models/team.py
pytfe/models/user.py
pytfe/models/variable.py
pytfe/models/variable_set.py
pytfe/models/workspace.py
pytfe/models/workspace_resource.py
pytfe/models/workspace_run_task.py
pytfe/resources/_base.py
pytfe/resources/agent_pools.py
pytfe/resources/agents.py
pytfe/resources/apply.py
pytfe/resources/configuration_version.py
pytfe/resources/notification_configuration.py
pytfe/resources/oauth_client.py
pytfe/resources/oauth_token.py
pytfe/resources/organization_membership.py
pytfe/resources/organizations.py
pytfe/resources/plan.py
pytfe/resources/policy.py
pytfe/resources/policy_check.py
pytfe/resources/policy_evaluation.py
pytfe/resources/policy_set.py
pytfe/resources/policy_set_outcome.py
pytfe/resources/policy_set_parameter.py
pytfe/resources/policy_set_version.py
pytfe-0.1.1.dist-info/METADATA
pytfe-0.1.1.dist-info/WHEEL
pytfe-0.1.1.dist-info/licenses/LICENSE
pytfe-0.1.1.dist-info/RECORD
