Metadata-Version: 2.4
Name: pytfe
Version: 0.1.1
Summary: Official Python SDK for HashiCorp Terraform Cloud / Terraform Enterprise (TFE) API v2
Project-URL: Repository, https://github.com/hashicorp/python-tfe
Project-URL: Bug Tracker, https://github.com/hashicorp/python-tfe/issues
Author: HashiCorp
License: MPL-2.0
License-File: LICENSE
Classifier: License :: OSI Approved :: Mozilla Public License 2.0 (MPL 2.0)
Classifier: Programming Language :: Python
Classifier: Programming Language :: Python :: 3
Classifier: Programming Language :: Python :: 3 :: Only
Classifier: Programming Language :: Python :: 3.10
Classifier: Programming Language :: Python :: 3.11
Classifier: Programming Language :: Python :: 3.12
Classifier: Programming Language :: Python :: 3.13
Requires-Python: >=3.10
Requires-Dist: h2>=4.3.0
Requires-Dist: httpx<0.29.0,>=0.27.0
Requires-Dist: pydantic<3,>=2.6
Requires-Dist: typing-extensions>=4.8
Provides-Extra: dev
Requires-Dist: mypy>=1.17.1; extra == 'dev'
Requires-Dist: pytest-mock>=3.14.1; extra == 'dev'
Requires-Dist: pytest>=7.0.0; extra == 'dev'
Requires-Dist: ruff>=0.12.10; extra == 'dev'
Requires-Dist: types-requests>=2.32.4.20250809; extra == 'dev'
